aagent/__init__.py
aagent/api.py
aagent/app.py
aagent/cli.py
aagent-0.0.0.dist-info/METADATA
aagent-0.0.0.dist-info/WHEEL
aagent-0.0.0.dist-info/entry_points.txt
aagent-0.0.0.dist-info/RECORD
