Metadata-Version: 2.1
Name: aagent
Version: 0.0.0
Summary: Actors and Agents combined.
Home-page: https://github.com/chatmangpt/aagent
Author: Sean Chatman
Author-email: info@chatmangpt.com
Requires-Python: >=3.11,<4.0
Classifier: Programming Language :: Python :: 3
Classifier: Programming Language :: Python :: 3.11
Classifier: Programming Language :: Python :: 3.12
Requires-Dist: coloredlogs (>=15.0.1)
Requires-Dist: fastapi[all] (>=0.92.0)
Requires-Dist: gunicorn (>=20.1.0)
Requires-Dist: poethepoet (>=0.20.0)
Requires-Dist: pydantic (>=1.10.7)
Requires-Dist: streamlit (>=1.19.0)
Requires-Dist: typer[all] (>=0.9.0)
Requires-Dist: uvicorn[standard] (>=0.20.0)
Project-URL: Repository, https://github.com/chatmangpt/aagent
